{"lobby_id":8721267126423880307,"ruleset_payload":{"filter":{"playlist_id":11,"matchmaking_version":"2.0","online_matchmaking_restrict":"","dw_build_name":"t8echoserver-all-all-all-0","netcode_version":2344,"dw_build_name_context":"t8-pc-wz-100","playlist_version":150059},"forced_empty":false},"dtls":{"security_id":"LdN2/gaS1EU=","security_key":"F6lYJOZaF4Hm8+gPu5k6YQ=="},"dedicated_server":{"build_name":"T8-ship-13869365-TU23-150059-49-5b0a31a1@2344","need_for_dedicated_server":"not_needed","data_center_preferences":[]},"player_id_to_slots":{"2075383531":1,"2292246268":1},"player_id_to_host_scores":{"2075383531":1,"2292246268":1},"players":{"2075383531":"expected","2292246268":"expected"},"player_id_to_mm_id":{"2075383531":12500487275696705779,"2292246268":5446573303204387488},"performance":{"game_type":1},"lobby_size":{"max":18,"min":2},"update_id":2,"update_time":1744846454000,"create_time":1744846456000}